{
  "collectionName": "components_home_component_testimonials",
  "info": {
    "displayName": "Testimonials",
    "icon": "align-justify",
    "description": ""
  },
  "options": {},
  "attributes": {
    "sectionHeader": {
      "type": "component",
      "repeatable": false,
      "component": "home-sub-component.section-header",
      "required": true
    },
    "testimonialCards": {
      "displayName": "testimonialCard",
      "type": "component",
      "repeatable": true,
      "component": "home-sub-component.testimonial-card",
      "required": true
    }
  }
}
